bitget/__init__.py
bitget/common/__init__.py
bitget/common/assets/__init__.py
bitget/common/assets/bot.py
bitget/common/assets/funding.py
bitget/common/assets/overview.py
bitget/common/tax/__init__.py
bitget/common/tax/futures_transaction_records.py
bitget/common/tax/margin_transaction_records.py
bitget/common/tax/p2p_transaction_records.py
bitget/common/tax/spot_transaction_records.py
bitget/copy/__init__.py
bitget/copy/futures/__init__.py
bitget/copy/futures/follower/__init__.py
bitget/copy/futures/follower/my_traders.py
bitget/copy/spot/__init__.py
bitget/copy/spot/follower/__init__.py
bitget/copy/spot/follower/my_traders.py
bitget/core/__init__.py
bitget/core/__init__.pyi
bitget/core/exc.py
bitget/core/mixin.py
bitget/core/rate_limiting.py
bitget/core/types.py
bitget/core/util.py
bitget/core/validation.py
bitget/core/http/__init__.py
bitget/core/http/__init__.pyi
bitget/core/http/auth.py
bitget/core/http/client.py
bitget/earn/__init__.py
bitget/earn/account/__init__.py
bitget/earn/account/assets.py
bitget/earn/savings/__init__.py
bitget/earn/savings/products.py
bitget/futures/__init__.py
bitget/futures/account/__init__.py
bitget/futures/account/account_list.py
bitget/futures/account/subaccount_assets.py
bitget/futures/market/__init__.py
bitget/futures/market/symbols.py
bitget/futures/position/__init__.py
bitget/futures/position/all_positions.py
bitget/futures/trade/__init__.py
bitget/futures/trade/fills.py
bitget/margin/__init__.py
bitget/margin/cross/__init__.py
bitget/margin/cross/account/__init__.py
bitget/margin/cross/account/assets.py
bitget/margin/cross/trade/__init__.py
bitget/margin/cross/trade/fills.py
bitget/margin/isolated/__init__.py
bitget/margin/isolated/account/__init__.py
bitget/margin/isolated/account/assets.py
bitget/margin/isolated/trade/__init__.py
bitget/margin/isolated/trade/fills.py
bitget/spot/__init__.py
bitget/spot/account/__init__.py
bitget/spot/account/assets.py
bitget/spot/account/deposit_records.py
typed_bitget-0.1.2.dist-info/METADATA
typed_bitget-0.1.2.dist-info/WHEEL
typed_bitget-0.1.2.dist-info/top_level.txt
typed_bitget-0.1.2.dist-info/RECORD
