Metadata-Version: 2.4
Name: typed-bitget
Version: 0.1.2
Summary: A fully typed, validated async client for the Bitget API.
Author-email: Marcel Claramunt <marcel@tribulnation.com>
Project-URL: repo, https://github.com/tribulnation/bitget.git
Requires-Python: >=3.10
Requires-Dist: lazy-loader
Requires-Dist: httpx
Requires-Dist: pydantic
Requires-Dist: websockets
Requires-Dist: orjson
